annotated_doc/__about__.py
annotated_doc/__init__.py
annotated_doc-0.0.1.dist-info/METADATA
annotated_doc-0.0.1.dist-info/WHEEL
annotated_doc-0.0.1.dist-info/licenses/LICENSE.txt
annotated_doc-0.0.1.dist-info/RECORD
